curlreq/__init__.py
curlreq/client.py
curlreq/compat.py
curlreq/cookies.py
curlreq/curl.py
curlreq/exceptions.py
curlreq/request.py
curlreq/response.py
curlreq/utils.py
curlreq/version.py
curlreq-0.1.0.dist-info/METADATA
curlreq-0.1.0.dist-info/WHEEL
curlreq-0.1.0.dist-info/top_level.txt
curlreq-0.1.0.dist-info/RECORD
